ot/__init__.py
ot/get.py
ot/identifier.py
ot_pie-0.1.0.dist-info/METADATA
ot_pie-0.1.0.dist-info/WHEEL
ot_pie-0.1.0.dist-info/RECORD
