Metadata-Version: 2.1
Name: ot-pie
Version: 0.1.0
Summary: 
Author: Steph Samson
Author-email: hi@kasteph.com
Requires-Python: >=3.12,<4.0
Classifier: Programming Language :: Python :: 3
Classifier: Programming Language :: Python :: 3.12
Requires-Dist: cbrrr (>=1.0.0,<2.0.0)
Requires-Dist: multiformats (>=0.3.1.post4,<0.4.0)
Requires-Dist: polars (>=1.6.0,<2.0.0)
